cuddly_octo_parent/__init__.py
cuddly_octo_parent-0.1.10.dist-info/METADATA
cuddly_octo_parent-0.1.10.dist-info/WHEEL
cuddly_octo_parent-0.1.10.dist-info/RECORD
