Metadata-Version: 2.1
Name: cuddly-octo-parent
Version: 0.1.10
Summary: 
Author: Vijay Lingesh
Author-email: vijay.lingesh@gausslabs.ai
Requires-Python: >=3.9,<4.0
Classifier: Programming Language :: Python :: 3
Classifier: Programming Language :: Python :: 3.9
Classifier: Programming Language :: Python :: 3.10
Classifier: Programming Language :: Python :: 3.11
Classifier: Programming Language :: Python :: 3.12
Requires-Dist: requests (>=2.32.3,<3.0.0)
